viviLibrary/__init__.py
viviLibrary/math_operations.py
viviLibrary-1.1.1.dist-info/METADATA
viviLibrary-1.1.1.dist-info/WHEEL
viviLibrary-1.1.1.dist-info/top_level.txt
viviLibrary-1.1.1.dist-info/RECORD
