Metadata-Version: 2.1
Name: viviLibrary
Version: 1.1.1
Summary: A library for basic math operations
Author: test user
